maxwell/__init__.py
maxwell/service/__init__.py
maxwell/service/config.py
maxwell/service/master_client.py
maxwell/service/publisher.py
maxwell/service/registrar.py
maxwell/service/server.py
maxwell/service/service.py
maxwell/service/topic_locatlizer.py
maxwell_service-0.12.3.dist-info/METADATA
maxwell_service-0.12.3.dist-info/WHEEL
maxwell_service-0.12.3.dist-info/licenses/LICENSE
maxwell_service-0.12.3.dist-info/RECORD
