Metadata-Version: 2.3
Name: maxwell-service
Version: 0.12.3
Summary: The maxwell service implementation for python.
Project-URL: changelog, https://github.com/maxwell-dev/maxwell-service-python/CHANGELOG.md
Project-URL: repository, https://github.com/maxwell-dev/maxwell-service-python
Author-email: Xu Chaoqian <chaoranxu@gmail.com>
License:                                  Apache License
License-File: LICENSE
Classifier: License :: OSI Approved :: MIT License
Classifier: Operating System :: OS Independent
Classifier: Programming Language :: Python :: 3
Requires-Python: >=3.7
Requires-Dist: async-lru>=2.0.4
Requires-Dist: fastapi[all]>=0.114.0
Requires-Dist: maxwell-protocol>=0.9.2
Requires-Dist: maxwell-utils>=0.8.1
Requires-Dist: setproctitle>=1.3.3
Requires-Dist: tomli>=2.0.1
Provides-Extra: test
Requires-Dist: pytest-asyncio>=0.24.0; extra == 'test'
Requires-Dist: pytest-cov>=5.0.0; extra == 'test'
Requires-Dist: pytest>=8.3.2; extra == 'test'
